codemonkeys/__init__.py
codemonkeys/__main__.py
codemonkeys/cm_paths.py
codemonkeys/defs.py
codemonkeys/types.py
codemonkeys/builders/__init__.py
codemonkeys/builders/committer.py
codemonkeys/builders/file_iterator.py
codemonkeys/builders/file_prompter.py
codemonkeys/builders/output_path_resolver.py
codemonkeys/builders/summarizer.py
codemonkeys/commands/__init__.py
codemonkeys/commands/gpt-models-info.py
codemonkeys/commands/list.py
codemonkeys/commands/make.py
codemonkeys/commands/print-monkey.py
codemonkeys/commands/version.py
codemonkeys/config/__init__.py
codemonkeys/config/env.py
codemonkeys/config/theme.py
codemonkeys/entities/__init__.py
codemonkeys/entities/automation.py
codemonkeys/entities/barrel.py
codemonkeys/entities/cli_runnable.py
codemonkeys/entities/command.py
codemonkeys/entities/func.py
codemonkeys/entities/monkey.py
codemonkeys/funcs/__init__.py
codemonkeys/funcs/extract_list.py
codemonkeys/funcs/finalize_output.py
codemonkeys/funcs/write_file.py
codemonkeys/help/__init__.py
codemonkeys/help/help.py
codemonkeys/help/commands/__init__.py
codemonkeys/help/commands/gpt-models-info.py
codemonkeys/help/commands/list.py
codemonkeys/help/commands/make.py
codemonkeys/help/commands/print-monkey.py
codemonkeys/help/commands/version.py
codemonkeys/scripts/__init__.py
codemonkeys/scripts/monk.py
codemonkeys/scripts/monk_new.py
codemonkeys/stor/__init__.py
codemonkeys/stor/defaults/._gitignore
codemonkeys/stor/defaults/.env
codemonkeys/stor/defaults/README.md
codemonkeys/stor/defaults/__init__.py
codemonkeys/stor/defaults/_requirements.txt
codemonkeys/stor/defaults/env.py
codemonkeys/stor/defaults/theme.py
codemonkeys/stor/defaults/automations/__init__.py
codemonkeys/stor/defaults/automations/default.py
codemonkeys/stor/defaults/automations/scaffold.py
codemonkeys/stor/defaults/commands/text-zip.py
codemonkeys/stor/defaults/monkeys/__init__.py
codemonkeys/stor/defaults/monkeys/finish_files.py
codemonkeys/stor/defaults/monkeys/monkey.py
codemonkeys-1.1.3.dist-info/LICENSE
codemonkeys-1.1.3.dist-info/METADATA
codemonkeys-1.1.3.dist-info/WHEEL
codemonkeys-1.1.3.dist-info/entry_points.txt
codemonkeys-1.1.3.dist-info/top_level.txt
codemonkeys-1.1.3.dist-info/RECORD
