Metadata-Version: 2.1
Name: codemonkeys
Version: 1.1.3
Summary: CodeMonkeys gives devs control over their automated GPT logic. The current focus is working on codebases but it is lovingly designed to enable automations of all kinds. This framework aims to use AI effectively, while being reliable, predictable, and tailored to your needs. There is a strong focus on only involving AI at crucial areas of strength, and using good old-fashioned code for everything else.
Home-page: https://github.com/cooleydw494/codemonkeys
Author: David Wallace Cooley Jr
Author-email: cooleydw494@gmail.com
License: MIT
Classifier: Development Status :: 3 - Alpha
Classifier: Intended Audience :: Developers
Classifier: License :: OSI Approved :: MIT License
Classifier: Programming Language :: Python :: 3
Classifier: Programming Language :: Python :: 3.6
Classifier: Programming Language :: Python :: 3.7
Classifier: Programming Language :: Python :: 3.8
Classifier: Programming Language :: Python :: 3.9
Requires-Python: >=3.6
License-File: LICENSE
Requires-Dist: openai
Requires-Dist: python-dotenv
Requires-Dist: Levenshtein
Requires-Dist: pandas
Requires-Dist: termcolor
Requires-Dist: tiktoken
Requires-Dist: psutil
Requires-Dist: json-repair
